README.txt
setup.py
PyWALS.egg-info/PKG-INFO
PyWALS.egg-info/SOURCES.txt
PyWALS.egg-info/dependency_links.txt
PyWALS.egg-info/top_level.txt
pywals/__init__.py
pywals/comparators.py
pywals/language.py
pywals/sqlmodel.py
pywals/wals.py
pywals/walszipparser.py