Metadata-Version: 1.1
Name: PyWALS
Version: 0.1.0
Summary: Pythonic interface to World Atlas of Language Structures
Home-page: https://github.com/lmaurits/pywals
Author: Luke Maurits
Author-email: luke@maurits.id.au
License: BSD (3 clause)
Platform: UNKNOWN
Classifier: Programming Language :: Python
Classifier: License :: OSI Approved :: BSD License
